Metadata-Version: 1.0
Name: pyseparator
Version: 0.12
Summary: pyseparator
Home-page: UNKNOWN
Author: lijun
Author-email: asdfzxcvqwer123a@126.com
License: MIT
Platform: UNKNOWN
